std_utils/__init__.py
std_utils/iter_utils.py
std_utils/py.typed
std_utils/utils.py
std_utils/benchmark/__init__.py
std_utils/benchmark/benchmark.py
std_utils/compression/__init__.py
std_utils/divide_and_conquer/__init__.py
std_utils/divide_and_conquer/divide_and_conquer.py
std_utils/memory/__init__.py
std_utils/memory/madv_constants.py
std_utils/memory/mmap_constants.py
std_utils/memory/shared_memory.py
std_utils/meta/__init__.py
std_utils/meta/abc.py
std_utils/models/__init__.py
std_utils/models/api.py
std_utils/models/async_models.py
std_utils/models/bases.py
std_utils/models/special.py
std_utils/multi/__init__.py
std_utils/multi/futex_lock.py
std_utils/multi/multi.py
std_utils/optimizations/__init__.py
std_utils/optimizations/opts.py
std_utils/packing/__init__.py
std_utils/packing/pack.py
std_utils/profiling/__init__.py
std_utils/profiling/profiling.py
std_utils/pseudofs/__init__.py
std_utils/pseudofs/cache.py
std_utils/pseudofs/constants.py
std_utils/pseudofs/models.py
std_utils/pseudofs/pseudofs.py
std_utils/std_collections/__init__.py
std_utils/std_collections/iteration.py
std_utils/std_collections/sequence.py
std_utils/std_types/__init__.py
std_utils/std_types/aliases.py
std_utils/std_types/float.py
std_utils/std_types/int.py
std_utils/std_types/numeric.py
std_utils/std_types/type_utils.py
std_python_utils-0.0.0.dist-info/LICENSE
std_python_utils-0.0.0.dist-info/METADATA
std_python_utils-0.0.0.dist-info/WHEEL
std_python_utils-0.0.0.dist-info/top_level.txt
std_python_utils-0.0.0.dist-info/RECORD
