Metadata-Version: 2.2
Name: std-python-utils
Version: 0.0.0
Author-email: Guy Wilson <guywilsonjr@gmail.com>
Maintainer-email: Guy Wilson <guywilsonjr@gmail.com>
Project-URL: Homepage, https://github.com/guywilsonjr/std-utils
Project-URL: Repository, https://github.com/guywilsonjr/std-utils
Classifier: Development Status :: 3 - Alpha
Classifier: Intended Audience :: Developers
Classifier: Intended Audience :: Information Technology
Classifier: License :: OSI Approved :: GNU General Public License v3 or later (GPLv3+)
Classifier: Operating System :: Unix
Classifier: Programming Language :: Python :: 3
Classifier: Programming Language :: Python :: 3.10
Classifier: Programming Language :: Python :: 3.11
Classifier: Programming Language :: Python :: 3.12
Classifier: Programming Language :: Python :: 3.13
Classifier: Topic :: System :: Systems Administration
Classifier: Topic :: System :: Monitoring
Classifier: Typing :: Typed
Requires-Python: >=3.12
License-File: LICENSE
Requires-Dist: aiofile
Requires-Dist: aiohttp
Requires-Dist: msgpack
Requires-Dist: numpy
Requires-Dist: pydantic
Requires-Dist: requests
